{"welcome":"Welcome on the framework Mora cli","select_lang":"Enter language:","usage":"Usage:","command":"command","lang_changed_success":"Language changed to English","firewall_add_success":"The firewall {name} was saved succesfully","firewall_check_comment":"return the required condition to pass the firewall","firewall_onfailed_comment":"Put the action to do if a this firewall is not passed","condition":"condition","controller_create_desc":"Create a new controller and set optionaly its actions","rename_required_names":"Old name and new name required.","firewall_not_found":"The firewall '{name}' cannot be found.","firewall_rename_success":"The firewall {old}'s name was changed to {new}.","firewall_name_conflict":"The name {name} is already used by another firewall.","controller_exists_prompt":"The controller {name} already exists.\r\nIf you continue, it will be overwriten.<nc>\r\nTry 'php mora controller add_actions action1[,action2...]' instead.\r\nContinue?(yes\/no)[<yellow>no<nc>]","ask_controller_name":"Enter the new controller's name:"}